Workbook

Sheet instance_results
A1: instance | B1: scenario | C1: total_profit_CNY | D1: sales_revenue_CNY | E1: external_procurement_cost_CNY | F1: external_procurement_quantity_t | G1: transport_cost_CNY
A2: 1 | B2: no_interplant | C2: 7.0617911e+08 | D2: 3.5784913e+09 | E2: 79160621 | F2: 2391100 | G2: 3.1717871e+08
A3: 1 | B3: full_interplant | C3: 7.7657297e+08 | D3: 3.5950777e+09 | E3: 29241388 | F3: 938800 | G3: 3.761532e+08
A4: 2 | B4: no_interplant | C4: 8.6430048e+08 | D4: 4.3622263e+09 | E4: 1.2336265e+08 | F4: 3764800 | G4: 3.9649326e+08
A5: 2 | B5: full_interplant | C5: 9.2971728e+08 | D5: 4.3688075e+09 | E5: 56633990 | F5: 1827600.1 | G5: 4.3163892e+08
A6: 3 | B6: no_interplant | C6: 8.6225824e+08 | D6: 4.2797407e+09 | E6: 1.5811736e+08 | F6: 4770200.1 | G6: 3.7805068e+08
A7: 3 | B7: full_interplant | C7: 9.3452554e+08 | D7: 4.3245163e+09 | E7: 78683022 | F7: 2505200 | G7: 4.4745214e+08
A8: 4 | B8: no_interplant | C8: 9.5033042e+08 | D8: 4.5179793e+09 | E8: 1.7675541e+08 | F8: 5280200 | G8: 3.8925507e+08
A9: 4 | B9: full_interplant | C9: 1.0001969e+09 | D9: 4.543572e+09 | E9: 1.2618299e+08 | F9: 3884800.2 | G9: 4.4112639e+08
A10: 5 | B10: no_interplant | C10: 8.3920083e+08 | D10: 4.3397867e+09 | E10: 1.598901e+08 | F10: 4844300.1 | G10: 3.7899064e+08
A11: 5 | B11: full_interplant | C11: 9.1106923e+08 | D11: 4.3547695e+09 | E11: 99765228 | F11: 3133600.1 | G11: 4.4923585e+08
A12: 6 | B12: no_interplant | C12: 9.0674383e+08 | D12: 4.3713619e+09 | E12: 1.9288307e+08 | F12: 5836800 | G12: 3.5176021e+08
A13: 6 | B13: full_interplant | C13: 9.9448129e+08 | D13: 4.3732601e+09 | E13: 74922543 | F13: 2390800.1 | G13: 4.1174412e+08
... A21: 10 | B21: full_interplant | C21: 1.3391685e+09 | D21: 6.2369315e+09 | E21: 1.9259354e+08 | F21: 6158400 | G21: 6.3972242e+08

Sheet scenario_averages
A1: scenario | B1: average_total_profit_CNY | C1: average_sales_revenue_CNY | D1: average_external_procurement_cost_CNY | E1: average_external_procurement_quantity_t | F1: average_transport_cost_CNY
A2: no_interplant | B2: =AVERAGEIF(instance_results!$B$2:$B$21,A2,instance_results!$C$2:$C$21) -> 9.7480232e+08 | C2: =AVERAGEIF(instance_results!$B$2:$B$21,A2,instance_results!$D$2:$D$21) -> 4.8449369e+09 | D2: =AVERAGEIF(instance_results!$B$2:$B$21,A2,instance_results!$E$2:$E$21) -> 1.9486995e+08 | E2: =AVERAGEIF(instance_results!$B$2:$B$21,A2,instance_results!$F$2:$F$21) -> 5936220.1 | F2: =AVERAGEIF(instance_results!$B$2:$B$21,A2,instance_results!$G$2:$G$21) -> 4.1769651e+08
A3: full_interplant | B3: =AVERAGEIF(instance_results!$B$2:$B$21,A3,instance_results!$C$2:$C$21) -> 1.058092e+09 | C3: =AVERAGEIF(instance_results!$B$2:$B$21,A3,instance_results!$D$2:$D$21) -> 4.8612522e+09 | D3: =AVERAGEIF(instance_results!$B$2:$B$21,A3,instance_results!$E$2:$E$21) -> 1.0681035e+08 | E3: =AVERAGEIF(instance_results!$B$2:$B$21,A3,instance_results!$F$2:$F$21) -> 3397480.1 | F3: =AVERAGEIF(instance_results!$B$2:$B$21,A3,instance_results!$G$2:$G$21) -> 4.8756163e+08

Sheet reported_changes
A1: metric | B1: no_interplant_average | C1: full_interplant_average | D1: relative_change
A2: Total profit | B2: =scenario_averages!B2 -> 9.7480232e+08 | C2: =scenario_averages!B3 -> 1.058092e+09 | D2: =IFERROR((C2-B2)/B2,0) -> 0.085442681
A3: External purchase cost | B3: =scenario_averages!D2 -> 1.9486995e+08 | C3: =scenario_averages!D3 -> 1.0681035e+08 | D3: =IFERROR((C3-B3)/B3,0) -> -0.45188908
A4: External purchase quantity | B4: =scenario_averages!E2 -> 5936220.1 | C4: =scenario_averages!E3 -> 3397480.1 | D4: =IFERROR((C4-B4)/B4,0) -> -0.42766946
A5: Transportation cost | B5: =scenario_averages!F2 -> 4.1769651e+08 | C5: =scenario_averages!F3 -> 4.8756163e+08 | D5: =IFERROR((C5-B5)/B5,0) -> 0.16726288
