Workbook

Sheet instance_results
A1: instance | B1: procurement_price | C1: scenario | D1: total_profit_CNY | E1: sales_revenue_CNY | F1: external_procurement_cost_CNY | G1: external_procurement_quantity_t | H1: transport_cost_CNY
A2: 1 | B2: low | C2: full_interplant | D2: 8.3645623e+08 | E2: 3.7171398e+09 | F2: 1.0310746e+08 | G2: 5568800 | H2: 3.8013249e+08
A3: 2 | B3: low | C3: full_interplant | D3: 1.0310329e+09 | E3: 4.5255016e+09 | F3: 1.6377022e+08 | G3: 9057600.1 | H3: 4.336364e+08
A4: 3 | B4: low | C4: full_interplant | D4: 1.0190352e+09 | E4: 4.4720489e+09 | F4: 1.6607882e+08 | G4: 9205200 | H4: 4.3627951e+08
A5: 4 | B5: low | C5: full_interplant | D5: 1.1479803e+09 | E5: 4.7920165e+09 | F5: 2.3032901e+08 | G5: 12524800 | H5: 4.4898488e+08
A6: 5 | B6: low | C6: full_interplant | D6: 1.0514699e+09 | E6: 4.6181147e+09 | F6: 2.2127063e+08 | G6: 12163200 | H6: 4.8022857e+08
A7: 6 | B7: low | C7: full_interplant | D7: 1.1427906e+09 | E7: 4.6768541e+09 | F7: 2.2625897e+08 | G7: 12460000 | H7: 4.3125997e+08
A8: 7 | B8: low | C8: full_interplant | D8: 1.4067655e+09 | E8: 5.7290661e+09 | F8: 3.4209368e+08 | G8: 18707600 | H8: 5.500534e+08
A9: 8 | B9: low | C9: full_interplant | D9: 1.3534998e+09 | E9: 5.8836593e+09 | F9: 3.4039355e+08 | G9: 18808800 | H9: 5.7719033e+08
A10: 9 | B10: low | C10: full_interplant | D10: 1.5961757e+09 | E10: 6.4500248e+09 | F10: 4.1532095e+08 | G10: 22888000 | H10: 6.1502668e+08
A11: 10 | B11: low | C11: full_interplant | D11: 1.6120673e+09 | E11: 6.6680376e+09 | F11: 4.2415111e+08 | G11: 23388400 | H11: 6.5388621e+08
A12: 1 | B12: low | C12: no_interplant | D12: 7.7492355e+08 | E12: 3.66942e+09 | F12: 1.0314771e+08 | G12: 5569500 | H12: 3.253968e+08
A13: 2 | B13: low | C13: no_interplant | D13: 9.7297218e+08 | E13: 4.5143781e+09 | F13: 1.6381609e+08 | G13: 9061700.1 | H13: 4.1119517e+08
... A61: 10 | B61: high | C61: no_interplant | D61: 1.1765459e+09 | E61: 5.8297775e+09 | F61: 14273974 | G61: 248300 | H61: 5.1029941e+08

Sheet scenario_averages
A1: procurement_price | B1: scenario | C1: average_total_profit_CNY | D1: average_sales_revenue_CNY | E1: average_external_procurement_cost_CNY | F1: average_external_procurement_quantity_t | G1: average_transport_cost_CNY
A2: low | B2: no_interplant | C2: =IFERROR(SUMIFS(instance_results!$D$2:$D$61,instance_results!$B$2:$B$61,A2,instance_results!$C$2:$C$61,B2)/COUNTIFS(instance_results!$B$2:$B$61,A2,instance_results!$C$2:$C$61,B2),0) -> 1.1598484e+09 | D2: =IFERROR(SUMIFS(instance_results!$E$2:$E$61,instance_results!$B$2:$B$61,A2,instance_results!$C$2:$C$61,B2)/COUNTIFS(instance_results!$B$2:$B$61,A2,instance_results!$C$2:$C$61,B2),0) -> 5.0878952e+09 | E2: =IFERROR(SUMIFS(instance_results!$F$2:$F$61,instance_results!$B$2:$B$61,A2,instance_results!$C$2:$C$61,B2)/COUNTIFS(instance_results!$B$2:$B$61,A2,instance_results!$C$2:$C$61,B2),0) -> 2.6400808e+08 | F2: =IFERROR(SUMIFS(instance_results!$G$2:$G$61,instance_results!$B$2:$B$61,A2,instance_results!$C$2:$C$61,B2)/COUNTIFS(instance_results!$B$2:$B$61,A2,instance_results!$C$2:$C$61,B2),0) -> 14508940 | G2: =IFERROR(SUMIFS(instance_results!$H$2:$H$61,instance_results!$B$2:$B$61,A2,instance_results!$C$2:$C$61,B2)/COUNTIFS(instance_results!$B$2:$B$61,A2,instance_results!$C$2:$C$61,B2),0) -> 4.3884165e+08
A3: low | B3: full_interplant | C3: =IFERROR(SUMIFS(instance_results!$D$2:$D$61,instance_results!$B$2:$B$61,A3,instance_results!$C$2:$C$61,B3)/COUNTIFS(instance_results!$B$2:$B$61,A3,instance_results!$C$2:$C$61,B3),0) -> 1.2197273e+09 | D3: =IFERROR(SUMIFS(instance_results!$E$2:$E$61,instance_results!$B$2:$B$61,A3,instance_results!$C$2:$C$61,B3)/COUNTIFS(instance_results!$B$2:$B$61,A3,instance_results!$C$2:$C$61,B3),0) -> 5.1532464e+09 | E3: =IFERROR(SUMIFS(instance_results!$F$2:$F$61,instance_results!$B$2:$B$61,A3,instance_results!$C$2:$C$61,B3)/COUNTIFS(instance_results!$B$2:$B$61,A3,instance_results!$C$2:$C$61,B3),0) -> 2.6327744e+08 | F3: =IFERROR(SUMIFS(instance_results!$G$2:$G$61,instance_results!$B$2:$B$61,A3,instance_results!$C$2:$C$61,B3)/COUNTIFS(instance_results!$B$2:$B$61,A3,instance_results!$C$2:$C$61,B3),0) -> 14477240 | G3: =IFERROR(SUMIFS(instance_results!$H$2:$H$61,instance_results!$B$2:$B$61,A3,instance_results!$C$2:$C$61,B3)/COUNTIFS(instance_results!$B$2:$B$61,A3,instance_results!$C$2:$C$61,B3),0) -> 5.0066784e+08
A4: base | B4: no_interplant | C4: =IFERROR(SUMIFS(instance_results!$D$2:$D$61,instance_results!$B$2:$B$61,A4,instance_results!$C$2:$C$61,B4)/COUNTIFS(instance_results!$B$2:$B$61,A4,instance_results!$C$2:$C$61,B4),0) -> 9.7630033e+08 | D4: =IFERROR(SUMIFS(instance_results!$E$2:$E$61,instance_results!$B$2:$B$61,A4,instance_results!$C$2:$C$61,B4)/COUNTIFS(instance_results!$B$2:$B$61,A4,instance_results!$C$2:$C$61,B4),0) -> 4.8446813e+09 | E4: =IFERROR(SUMIFS(instance_results!$F$2:$F$61,instance_results!$B$2:$B$61,A4,instance_results!$C$2:$C$61,B4)/COUNTIFS(instance_results!$B$2:$B$61,A4,instance_results!$C$2:$C$61,B4),0) -> 1.9312341e+08 | F4: =IFERROR(SUMIFS(instance_results!$G$2:$G$61,instance_results!$B$2:$B$61,A4,instance_results!$C$2:$C$61,B4)/COUNTIFS(instance_results!$B$2:$B$61,A4,instance_results!$C$2:$C$61,B4),0) -> 5875190 | G4: =IFERROR(SUMIFS(instance_results!$H$2:$H$61,instance_results!$B$2:$B$61,A4,instance_results!$C$2:$C$61,B4)/COUNTIFS(instance_results!$B$2:$B$61,A4,instance_results!$C$2:$C$61,B4),0) -> 4.1820575e+08
A5: base | B5: full_interplant | C5: =IFERROR(SUMIFS(instance_results!$D$2:$D$61,instance_results!$B$2:$B$61,A5,instance_results!$C$2:$C$61,B5)/COUNTIFS(instance_results!$B$2:$B$61,A5,instance_results!$C$2:$C$61,B5),0) -> 1.0572367e+09 | D5: =IFERROR(SUMIFS(instance_results!$E$2:$E$61,instance_results!$B$2:$B$61,A5,instance_results!$C$2:$C$61,B5)/COUNTIFS(instance_results!$B$2:$B$61,A5,instance_results!$C$2:$C$61,B5),0) -> 4.8620506e+09 | E5: =IFERROR(SUMIFS(instance_results!$F$2:$F$61,instance_results!$B$2:$B$61,A5,instance_results!$C$2:$C$61,B5)/COUNTIFS(instance_results!$B$2:$B$61,A5,instance_results!$C$2:$C$61,B5),0) -> 1.0742771e+08 | F5: =IFERROR(SUMIFS(instance_results!$G$2:$G$61,instance_results!$B$2:$B$61,A5,instance_results!$C$2:$C$61,B5)/COUNTIFS(instance_results!$B$2:$B$61,A5,instance_results!$C$2:$C$61,B5),0) -> 3424240 | G5: =IFERROR(SUMIFS(instance_results!$H$2:$H$61,instance_results!$B$2:$B$61,A5,instance_results!$C$2:$C$61,B5)/COUNTIFS(instance_results!$B$2:$B$61,A5,instance_results!$C$2:$C$61,B5),0) -> 4.882504e+08
A6: high | B6: no_interplant | C6: =IFERROR(SUMIFS(instance_results!$D$2:$D$61,instance_results!$B$2:$B$61,A6,instance_results!$C$2:$C$61,B6)/COUNTIFS(instance_results!$B$2:$B$61,A6,instance_results!$C$2:$C$61,B6),0) -> 9.4082044e+08 | D6: =IFERROR(SUMIFS(instance_results!$E$2:$E$61,instance_results!$B$2:$B$61,A6,instance_results!$C$2:$C$61,B6)/COUNTIFS(instance_results!$B$2:$B$61,A6,instance_results!$C$2:$C$61,B6),0) -> 4.5837799e+09 | E6: =IFERROR(SUMIFS(instance_results!$F$2:$F$61,instance_results!$B$2:$B$61,A6,instance_results!$C$2:$C$61,B6)/COUNTIFS(instance_results!$B$2:$B$61,A6,instance_results!$C$2:$C$61,B6),0) -> 11549916 | F6: =IFERROR(SUMIFS(instance_results!$G$2:$G$61,instance_results!$B$2:$B$61,A6,instance_results!$C$2:$C$61,B6)/COUNTIFS(instance_results!$B$2:$B$61,A6,instance_results!$C$2:$C$61,B6),0) -> 199580 | G6: =IFERROR(SUMIFS(instance_results!$H$2:$H$61,instance_results!$B$2:$B$61,A6,instance_results!$C$2:$C$61,B6)/COUNTIFS(instance_results!$B$2:$B$61,A6,instance_results!$C$2:$C$61,B6),0) -> 3.960184e+08
A7: high | B7: full_interplant | C7: =IFERROR(SUMIFS(instance_results!$D$2:$D$61,instance_results!$B$2:$B$61,A7,instance_results!$C$2:$C$61,B7)/COUNTIFS(instance_results!$B$2:$B$61,A7,instance_results!$C$2:$C$61,B7),0) -> 1.0446103e+09 | D7: =IFERROR(SUMIFS(instance_results!$E$2:$E$61,instance_results!$B$2:$B$61,A7,instance_results!$C$2:$C$61,B7)/COUNTIFS(instance_results!$B$2:$B$61,A7,instance_results!$C$2:$C$61,B7),0) -> 4.7652851e+09 | E7: =IFERROR(SUMIFS(instance_results!$F$2:$F$61,instance_results!$B$2:$B$61,A7,instance_results!$C$2:$C$61,B7)/COUNTIFS(instance_results!$B$2:$B$61,A7,instance_results!$C$2:$C$61,B7),0) -> 5284788.4 | F7: =IFERROR(SUMIFS(instance_results!$G$2:$G$61,instance_results!$B$2:$B$61,A7,instance_results!$C$2:$C$61,B7)/COUNTIFS(instance_results!$B$2:$B$61,A7,instance_results!$C$2:$C$61,B7),0) -> 90439.992 | G7: =IFERROR(SUMIFS(instance_results!$H$2:$H$61,instance_results!$B$2:$B$61,A7,instance_results!$C$2:$C$61,B7)/COUNTIFS(instance_results!$B$2:$B$61,A7,instance_results!$C$2:$C$61,B7),0) -> 4.838918e+08
